README.rst
setup.py
ckanext/__init__.py
ckanext/sentry/__init__.py
ckanext/sentry/plugins.py
ckanext_sentry.egg-info/PKG-INFO
ckanext_sentry.egg-info/SOURCES.txt
ckanext_sentry.egg-info/dependency_links.txt
ckanext_sentry.egg-info/entry_points.txt
ckanext_sentry.egg-info/namespace_packages.txt
ckanext_sentry.egg-info/not-zip-safe
ckanext_sentry.egg-info/requires.txt
ckanext_sentry.egg-info/top_level.txt