Metadata-Version: 1.1
Name: ckanext-sentry
Version: 0.0.1
Summary: Sentry support for CKAN
Home-page: https://github.com/okfn/ckanext-sentry
Author: Adrià Mercader
Author-email: adria.mercader@okfn.org
License: UNKNOWN
Keywords: CKAN,Sentry
Platform: UNKNOWN
Classifier: Development Status :: 3 - Alpha
Classifier: Environment :: Web Environment
Classifier: Framework :: Pylons
Classifier: Intended Audience :: Developers
Classifier: Programming Language :: Python :: 2
Classifier: Programming Language :: Python :: 2.7
Classifier: Programming Language :: Python
Classifier: Topic :: Internet :: WWW/HTTP :: Session
Classifier: Topic :: Internet :: WWW/HTTP :: WSGI :: Middleware
Classifier: Topic :: Software Development :: Libraries :: Python Modules
Classifier: Topic :: System :: Systems Administration :: Authentication/Directory
